odoo10_addon_mrp_auto_assign-10.0.1.0.0-py2.7-nspkg.pth
odoo/addons/mrp_auto_assign/README.rst
odoo/addons/mrp_auto_assign/__init__.py
odoo/addons/mrp_auto_assign/__manifest__.py
odoo/addons/mrp_auto_assign/models/__init__.py
odoo/addons/mrp_auto_assign/models/mrp_production.py
odoo/addons/mrp_auto_assign/tests/__init__.py
odoo/addons/mrp_auto_assign/tests/test_auto_assign.py
odoo10_addon_mrp_auto_assign-10.0.1.0.0.dist-info/DESCRIPTION.rst
odoo10_addon_mrp_auto_assign-10.0.1.0.0.dist-info/METADATA
odoo10_addon_mrp_auto_assign-10.0.1.0.0.dist-info/RECORD
odoo10_addon_mrp_auto_assign-10.0.1.0.0.dist-info/WHEEL
odoo10_addon_mrp_auto_assign-10.0.1.0.0.dist-info/metadata.json
odoo10_addon_mrp_auto_assign-10.0.1.0.0.dist-info/namespace_packages.txt
odoo10_addon_mrp_auto_assign-10.0.1.0.0.dist-info/top_level.txt
